zyjn_ans/__init__.py
zyjn_ans/core.py
zyjn_ans/data/Model4.py
zyjn_ans/data/task1_1_ans.py
zyjn_ans/data/task1_2_ans.py
zyjn_ans/data/task2.py
zyjn_ans/data/task2_ans.py
zyjn_ans/data/task3_ans.py
zyjn_ans-1.0.1.dist-info/METADATA
zyjn_ans-1.0.1.dist-info/WHEEL
zyjn_ans-1.0.1.dist-info/top_level.txt
zyjn_ans-1.0.1.dist-info/RECORD
